[
  {
    "id": "A1-Admin",
    "assetId": 101186560091322,
    "nombre": "Wapote",
    "image": "rbxassetid://140163736858344"
  },
  {
    "id": "A2-Admin",
    "assetId": 126598154439785,
    "nombre": "TORETO",
    "image": "rbxassetid://120325330496532"
  },
  {
    "id": "A3-Admin",
    "assetId": 88021546936115,
    "nombre": "CARE",
    "image": "rbxassetid://84685388679840"
  },
  {
    "id": "A1",
    "assetId": 97238756208481,
    "nombre": "Toyobobo FJ2025",
    "image": "rbxassetid://132278783679098"
  },
  {
    "id": "A2",
    "assetId": 99195634219434,
    "nombre": "Jeepeta XJ",
    "image": "rbxassetid://99522426985330",
    "shop": true,
    "price": 50000 
  },
  {
    "id": "A3",
    "assetId": 140063387835267,
    "nombre": "Bachaquero",
    "image": "rbxassetid://83463752811667",
    "shop": true,
    "price": 90000 
  },
  {
    "id": "A4",
    "assetId": 96439649900509,
    "nombre": "Blazer Viajero",
    "image": "rbxassetid://96304475720791",
    "shop": true,
    "price": 35000 
  },
  {
    "id": "A5",
    "assetId": 132428401013922,
    "nombre": "PorPuesto",
    "image": "rbxassetid://76021463683906",
    "shop": true,
    "price": 20000 
  },
  {
    "id": "A6",
    "assetId": 131900859754228,
    "nombre": "Versus SF Sport",
    "image": "rbxassetid://113230894979356",
    "shop": true,
    "price": 190000 
  },
  {
    "id": "A7",
    "assetId": 118409410538594,
    "nombre": "Jeepeta YJ Full",
    "image": "rbxassetid://76141401658505",
    "shop": true,
    "price": 150000 
  },
  {
    "id": "A8",
    "assetId": 134477756280488,
    "nombre": "Jeepeta YJ",
    "image": "rbxassetid://123792257869158",
    "shop": true,
    "price": 100000 
  },
  {
    "id": "A9",
    "assetId": 96336118942945,
    "nombre": "Explorer",
    "image": "rbxassetid://115316593642044",
    "shop": true,
    "price": 70000 
  }
]
